{
  "id": "json-editor-form",
  "title": {
    "en": "Form editor for JSON config",
    "ru": "Форма редактирования JSON конфигурации"
  },
  "description": {
    "en": ""
  },
  "customModule": null,
  "typeRef": "emodel/type@base",
  "width": "default",
  "i18n": {},
  "definition": {
    "components": [
      {
        "columns": [
          {
            "components": [
              {
                "className": "alert alert-info",
                "content": "<li>You're going to edit config of this record like JSON. Be careful.</li>\n<li>If you change ID, this configuration won't be changed, there will be new configuration based on this.</li>",
                "refreshOnChange": false,
                "refreshOn": [],
                "key": "html",
                "type": "htmlelement",
                "input": false
              }
            ],
            "type": "column",
            "input": false,
            "key": "column",
            "index": 0,
            "md": 0
          }
        ],
        "key": "columns2",
        "type": "columns",
        "input": false
      },
      {
        "label": "Record Configuration",
        "editor": "ace",
        "wysiwyg": "",
        "customClass": "ecos-json-editor-expand",
        "persistent": false,
        "defaultValue": "{}",
        "refreshOn": [],
        "calculateValue": "value = _.get(data, 'configJson._config');",
        "allowCalculateOverride": true,
        "key": "configuration",
        "logic": [
          {
            "name": "disabled",
            "trigger": {
              "type": "javascript",
              "javascript": "result = _.isEmpty(data.configJson)"
            },
            "actions": [
              {
                "name": "disable",
                "type": "property",
                "property": {
                  "label": "Disabled",
                  "value": "disabled",
                  "type": "boolean"
                },
                "state": "true"
              }
            ]
          }
        ],
        "rows": 40,
        "as": "json",
        "type": "textarea",
        "customStyle": "{background: 'green' }",
        "input": true
      },
      {
        "columns": [
          {
            "components": [
              {
                "label": "Full Screen",
                "removeIndents": true,
                "action": "custom",
                "state": "",
                "showValidations": false,
                "custom": "if (!document.fullscreenElement) {\r\n  document.querySelector('.ecos-json-editor-expand .formio-wysiwyg-editor').requestFullscreen();\r\n} else {\r\n  if (document.exitFullscreen) {\r\n    document.exitFullscreen();\r\n  }\r\n}",
                "leftIcon": "fa fa-arrows-alt",
                "refreshOn": [],
                "key": "submit2",
                "type": "button",
                "input": true
              }
            ],
            "md": 10,
            "type": "column",
            "input": false,
            "key": "column",
            "index": 0
          },
          {
            "md": 2,
            "type": "column",
            "input": false,
            "key": "column",
            "index": 1,
            "components": [
              {
                "state": "",
                "theme": "primary",
                "block": true,
                "disableOnInvalid": true,
                "refreshOn": [],
                "key": "submit",
                "type": "button",
                "input": true
              }
            ]
          }
        ],
        "key": "columns3",
        "type": "columns",
        "input": false
      },
      {
        "label": "getJson",
        "source": {
          "type": "record",
          "record": {
            "id": "{{recordId}}",
            "attributes": {
              "_config": ".json"
            }
          },
          "forceLoad": false
        },
        "update": {
          "type": "once",
          "rate": 1000
        },
        "executionCondition": "value = _.isEmpty(data.configJson);",
        "key": "configJson",
        "type": "asyncData",
        "input": true
      }
    ]
  },
  "attributes": {}
}
